[
  {
    "id": "vza2RIzNGIwutCVCs4mCL",
    "name": "Wylie Pope",
    "email": "est@utquamvel.net",
    "phone": "(692) 802-2949"
  },
  {
    "id": "05olLMgyVQdWRwgKfg5J6",
    "name": "Cyrus Jackson",
    "email": "nibh@semsempererat.com",
    "phone": "(501) 472-5218"
  },
  {
    "id": "1DEXoP8AuCGYc1YgoQ6hw",
    "name": "Abbot Franks",
    "email": "scelerisque@magnis.org",
    "phone": "(186) 568-3720"
  },
  {
    "id": "Z5sbDlS7pCzNsnAHLtDJd",
    "name": "Reuben Henry",
    "email": "pharetra.ut@dictum.co.uk",
    "phone": "(715) 598-5792"
  },
  {
    "id": "C9sjBfCo4UJCWjzBnOtxl",
    "name": "Simon Morton",
    "email": "dui.Fusce.diam@Donec.com",
    "phone": "(233) 738-2360"
  },
  {
    "id": "e6ywwRe4jcqxXfCZOj_1e",
    "name": "Thomas Lucas",
    "email": "nec@Nulla.com",
    "phone": "(704) 398-7993"
  },
  {
    "id": "rsKkOQUi80UsgVPCcLZZW",
    "name": "Alec Howard",
    "email": "Donec.elementum@scelerisquescelerisquedui.net",
    "phone": "(748) 206-2688"
  },
  {
    "name": {
      "name": "alan wake",
      "phone": "999999999"
    },
    "id": "ddf59eb3-4ab7-46f8-b9de-9464f0e82248"
  },
  {
    "name": {
      "name": "alan dou",
      "email": "alan@mail.com",
      "phone": "9999999999"
    },
    "id": "5b1eeb1d-5038-4149-866e-f0c3bb7fbf67"
  },
  {
    "name": {
      "name": "alan",
      "email": "alan@mail.com",
      "phone": "9999999999"
    },
    "id": "73e79f81-384a-42b1-a54d-b7c3b8c805eb"
  },
  {
    "name": {
      "name": "alan aaaa",
      "email": "alan@mail.com",
      "phone": "9999999999"
    },
    "id": "d667f5ad-5332-40ab-acf6-4e421eeafaa8"
  },
  {
    "name": {
      "name": "alan vvvv",
      "email": "alan@mail.com",
      "phone": "9999999999"
    },
    "id": "041020ef-9f26-411e-a198-3d016e78cb9c"
  },
  {
    "name": {
      "name": "alan bbbb",
      "email": "alan@mail.com",
      "phone": "9999999999"
    },
    "id": "93316206-0dce-423c-888b-fc9dffdc68e3"
  },
  {
    "name": {
      "name": "alan bbbb",
      "email": "alan@mail.com",
      "phone": "9999999999"
    },
    "id": "89cd2330-bc9e-49bc-8b44-fa302b91cb17"
  },
  {
    "name": {
      "name": "alan bbbb",
      "email": "alan@mail.com",
      "phone": "9999999999"
    },
    "id": "7fc61b74-be1e-4c70-b62e-ac1c851a0e51"
  },
  {
    "name": {
      "name": "alan cccc",
      "email": "alan@mail.com",
      "phone": "9999999999"
    },
    "id": "1a74ed6e-f7a8-4fce-b666-7be1583b32bc"
  },
  {
    "name": "alan qqqq",
    "email": "alan@mail.com",
    "phone": "9999999999",
    "id": "dea32a4a-47fe-4c36-9238-2f739aed0c90"
  },
  {
    "name": "alan qqqq",
    "email": "alan@mail.com",
    "phone": "9999999999",
    "id": "c8efff17-31b5-401d-8b2d-020a9be47808"
  },
  {
    "id": "70ef7505-b32c-41c4-ba5d-d99b06614105",
    "name": "alan",
    "email": "alan@mail.com",
    "phone": "9999999999"
  }
]